README.md
setup.py
pcommon/__init__.py
pcommon/file.py
pcommon/logger.py
pcommon/mysql.py
pcommon/response.py
pcommon.egg-info/PKG-INFO
pcommon.egg-info/SOURCES.txt
pcommon.egg-info/dependency_links.txt
pcommon.egg-info/top_level.txt