Metadata-Version: 2.1
Name: pcommon
Version: 0.0.3
Summary: A python tool package
Home-page: https://github.com/shijianliangs/pcommon
Author: shijianliangs
Author-email: shijianliangs@gmail.com
License: UNKNOWN
Platform: UNKNOWN
Classifier: Programming Language :: Python :: 3
Classifier: License :: OSI Approved :: MIT License
Classifier: Operating System :: OS Independent
Requires-Python: >=3.6
